cheatsheets/__init__.py
cheatsheets/__main__.py
cheatsheets/cheatsheets.py
cheatsheets/wizard.py
cheatsheets-0.0.4.dist-info/LICENSE.txt
cheatsheets-0.0.4.dist-info/METADATA
cheatsheets-0.0.4.dist-info/WHEEL
cheatsheets-0.0.4.dist-info/entry_points.txt
cheatsheets-0.0.4.dist-info/top_level.txt
cheatsheets-0.0.4.dist-info/RECORD
