Metadata-Version: 2.1
Name: cheatsheets
Version: 0.0.4
Summary: Cheatsheets
Home-page: https://github.com/Tlalocan/cheatsheets
Author: Tlaloc-Es
Author-email: 
License: MIT
Platform: UNKNOWN
Classifier: License :: OSI Approved :: MIT License
Classifier: Programming Language :: Python :: 3
Classifier: Programming Language :: Python :: 3.8
Requires-Dist: simple-term-menu
Requires-Dist: pygments
Requires-Dist: click
